dataloaders/cell_img_mask_loader.py
dataloaders/naive_pngnpy_loader.py
dataloaders/pngnpy_loaderV1.py
dataloaders/pngnpy_loaderV2.py
dataloaders/pngnpy_loader_cellnuc.py
dataloaders/pngtif_loader.py
models/__init__.py
models/unicell_modules.py
optimizers/__init__.py
optimizers/lr_scheduler.py
unicell-0.0.1.post0.dist-info/LICENSE
unicell-0.0.1.post0.dist-info/METADATA
unicell-0.0.1.post0.dist-info/WHEEL
unicell-0.0.1.post0.dist-info/entry_points.txt
unicell-0.0.1.post0.dist-info/top_level.txt
unicell-0.0.1.post0.dist-info/RECORD
