Metadata-Version: 2.1
Name: unicell
Version: 0.0.1.post0
Summary: Universal cell segmentation
Home-page: 
Author: Jun Ma
Author-email: 1259389904@qq.com
License: MIT
Platform: all
License-File: LICENSE
Requires-Dist: monai
Requires-Dist: numpy
Requires-Dist: imagecodecs
Requires-Dist: scipy
Requires-Dist: scikit-image
Requires-Dist: pillow
Requires-Dist: tensorboard
Requires-Dist: gdown
Requires-Dist: torchvision
Requires-Dist: tqdm
Requires-Dist: psutil
Requires-Dist: pandas
Requires-Dist: einops
Requires-Dist: numba
Requires-Dist: matplotlib
